pyzcode/__init__.py
pyzcode/data/zip_code_database.csv
pyzcode/data_loader.py
pyzcode/distance.py
pyzcode/exceptions.py
pyzcode/query.py
pyzcode/utils.py
pyzcode-0.7.0.dist-info/LICENSE
pyzcode-0.7.0.dist-info/METADATA
pyzcode-0.7.0.dist-info/WHEEL
pyzcode-0.7.0.dist-info/RECORD
