Metadata-Version: 2.1
Name: pyzcode
Version: 0.7.0
Summary: Python package to manage zip codes
License: Apache 2.0
Author: Youssef Ragab
Author-email: 77282699+youssefragab99@users.noreply.github.com
Requires-Python: >=3.9,<4.0
Classifier: License :: Other/Proprietary License
Classifier: Programming Language :: Python :: 3
Classifier: Programming Language :: Python :: 3.9
Classifier: Programming Language :: Python :: 3.10
Classifier: Programming Language :: Python :: 3.11
Classifier: Programming Language :: Python :: 3.12
Classifier: Programming Language :: Python :: 3.13
Requires-Dist: pandas (>=2.2.3,<3.0.0)
Requires-Dist: poetry-bumpversion (>=0.3.2,<0.4.0)
